sibylla/__init__.py
sibylla-0.0.1.dist-info/LICENSE
sibylla-0.0.1.dist-info/METADATA
sibylla-0.0.1.dist-info/WHEEL
sibylla-0.0.1.dist-info/top_level.txt
sibylla-0.0.1.dist-info/RECORD
